README.txt
setup.py
OneSheet.egg-info/PKG-INFO
OneSheet.egg-info/SOURCES.txt
OneSheet.egg-info/dependency_links.txt
OneSheet.egg-info/pbr.json
OneSheet.egg-info/top_level.txt
onesheet/AUXMetadata.py
onesheet/AudioMetadata.py
onesheet/AudioObject.py
onesheet/CRSMetadata.py
onesheet/ClassFileMetadata.py
onesheet/DocumentMetadata.py
onesheet/DublinCoreMetadata.py
onesheet/EXFMetadata.py
onesheet/FileObject.py
onesheet/ImageMetadata.py
onesheet/ImageObject.py
onesheet/OExceptions.py
onesheet/PDFMetadata.py
onesheet/PDFObject.py
onesheet/PhotoshopMetadata.py
onesheet/TimeBasedMetadata.py
onesheet/VideoMetadata.py
onesheet/VideoObject.py
onesheet/XMPAudioMetadata.py
onesheet/XMPImageMetadata.py
onesheet/XMPMetadata.py
onesheet/XMPVideoMetadata.py
onesheet/__init__.py
onesheet/test_timeBasedMetadata.py