Metadata-Version: 1.1
Name: OneSheet
Version: 0.1.5.7
Summary: Easily access metadata for image, video, sound, and document file.
Home-page: https://github.com/henryborchers/OneSheet
Author: Henry Borchers
Author-email: henryborchers@yahoo.com
License: GPL3
Keywords: metadata extraction
Platform: UNKNOWN
Classifier: Development Status :: 2 - Pre-Alpha
Classifier: License :: OSI Approved :: GNU General Public License v3 (GPLv3)
Classifier: Programming Language :: Python
Classifier: Topic :: Multimedia :: Sound/Audio :: Analysis
